topsis_yatharth_102303136/__init__.py
topsis_yatharth_102303136/topsis.py
topsis_yatharth_102303136-0.0.1.dist-info/licenses/LICENSE
topsis_yatharth_102303136-0.0.1.dist-info/METADATA
topsis_yatharth_102303136-0.0.1.dist-info/WHEEL
topsis_yatharth_102303136-0.0.1.dist-info/entry_points.txt
topsis_yatharth_102303136-0.0.1.dist-info/top_level.txt
topsis_yatharth_102303136-0.0.1.dist-info/RECORD
